faxbot/__init__.py
faxbot/plugins.py
faxbot-1.1.0.dist-info/METADATA
faxbot-1.1.0.dist-info/WHEEL
faxbot-1.1.0.dist-info/top_level.txt
faxbot-1.1.0.dist-info/RECORD
