Metadata-Version: 2.4
Name: faxbot
Version: 1.1.0
Summary: Faxbot API Client SDK for Python
Home-page: https://github.com/DMontgomery40/Faxbot
Author: David Montgomery
Author-email: dmontg@gmail.com
Classifier: Programming Language :: Python :: 3
Classifier: License :: OSI Approved :: MIT License
Classifier: Operating System :: OS Independent
Classifier: Topic :: Communications :: Fax
Classifier: Intended Audience :: Developers
Requires-Python: >=3.7
Requires-Dist: requests>=2.20.0
Dynamic: author
Dynamic: author-email
Dynamic: classifier
Dynamic: description
Dynamic: description-content-type
Dynamic: home-page
Dynamic: requires-dist
Dynamic: requires-python
Dynamic: summary
